Workbook

Sheet safari_english
A1: Participant Information | C1: Q1. English Captured Stereotypes | D1: Stereotype Breakdown | G1: Q2. Offensiveness | H1: Q3. Prevalence | I1: Additional Comments and Context | J1: Q1.1 Local Language Specific (Slang terms)
A2: Country Name | B2: Unique Identifier | C2: Please capture the complete Stereotype sentence in English mentioned by the participant | D2: Stereotype Identity Term | E2: Stereotype Attribute | F2: Stereotype Identity Axis | G2: How offensive is this stereotype? (1-5) | H2: How widely used/common/popular is this stereotype? (1-4) | I2: Any additional context or background that could help understand the stereotype | J2: Any slang or local language-specific stereotypes mentioned | K2: Slang term meaning (Post-interview)
A3: Ghana | B3: GH0019 | C3: People from the Upper West Region don't like schooling | D3: People From Upper West | E3: Dislike schooling | F3: Region | G3: 5 - Extremely offensive | H3: 1 - Rarely used
A4: Ghana | B4: GH0019 | C4: People from the North are perceived to be Muslims | D4: Northeners | E4: Muslim | F4: Region | G4: 4 - Somewhat offensive | H4: 3 - Commonly used
A5: Ghana | B5: GH0019 | C5: Northerners are ugly | D5: Northeners | E5: Ugly | F5: Region | G5: 5 - Extremely offensive | H5: 1 - Rarely used
A6: Ghana | B6: GH0019 | C6: Gas are loud | D6: Gas | E6: Loud | F6: Ethnicity | G6: 5 - Extremely offensive | H6: 4 - Extremely prevalent/popular
A7: Ghana | B7: GH0019 | C7: Gas are lazy | D7: Gas | E7: Lazy | F7: Ethnicity | G7: 3 - Slightly offensive | H7: 3 - Commonly used
A8: Ghana | B8: GH0019 | C8: Politics is meant for men | D8: Men | E8: Politicians | F8: Gender | G8: 4 - Somewhat offensive | H8: 3 - Commonly used
A9: Ghana | B9: GH0019 | C9: All Engineering work is meant for men | D9: Men | E9: Engineers | F9: Gender | G9: 4 - Somewhat offensive | H9: 3 - Commonly used
A10: Ghana | B10: GH0019 | C10: Women are meant to be in the kitchen | D10: Women | E10: Kitchen work | F10: Gender | G10: 5 - Extremely offensive | H10: 4 - Extremely prevalent/popular
A11: Ghana | B11: GH0019 | C11: Nursing is meant for women | D11: Women | E11: Nursing | F11: Gender | G11: 4 - Somewhat offensive | H11: 3 - Commonly used
A12: Ghana | B12: GH0019 | C12: Ghanaians are peaceful people | D12: Ghanaians | E12: Peaceful | F12: Nationality | G12: 1 - Not offensive | H12: 3 - Commonly used
A13: Ghana | B13: GH0099 | C13: All Northerners are lazy | D13: Northeners | E13: Lazy | F13: Region | G13: 5 - Extremely offensive | H13: 3 - Commonly used
A14: Ghana | B14: GH0099 | C14: All Northerners are violent | D14: Northeners | E14: Violent | F14: Region | G14: 3 - Slightly offensive | H14: 3 - Commonly used
A15: Ghana | B15: GH0099 | C15: Ashanti people like cursing people | D15: Ashantis | E15: Like cursing people | F15: Ethnicity | G15: 1 - Not offensive | H15: 4 - Extremely prevalent/popular | I15: This refers to curses wishing harm or bad consequences on people
A16: Ghana | B16: GH0099 | C16: Nigerians are fraudsters | D16: Nigerians | E16: Fraudsters | F16: Nationality | G16: 3 - Slightly offensive | H16: 4 - Extremely prevalent/popular
A17: Ghana | B17: GH0099 | C17: Igbos from Nigeria are hardworking | D17: Igbos | E17: Hardworking | F17: Ethnicity | G17: 1 - Not offensive | H17: 3 - Commonly used
A18: Ghana | B18: GH0099 | C18: Mulims don't like education | D18: Muslims | E18: Dislike Education | F18: Religion | G18: 5 - Extremely offensive | H18: 4 - Extremely prevalent/popular
A19: Ghana | B19: GH0099 | C19: Muslims don't like their daughters to marry from other religions | D19: Muslims | E19: Dislike daughters marrying from other religions | F19: Religion | G19: 1 - Not offensive | H19: 4 - Extremely prevalent/popular
A20: Ghana | B20: GH0099 | C20: Female bosses are strict | D20: Female Bosses | E20: Strict | F20: Gender, Profession | G20: 3 - Slightly offensive | H20: 3 - Commonly used
A21: Ghana | B21: GH0099 | C21: Policticians are liars | D21: Politicians | E21: Liars | F21: Profession | G21: 5 - Extremely offensive | H21: 4 - Extremely prevalent/popular
A22: Ghana | B22: GH0099 | C22: Nigerians are violent | D22: Nigerians | E22: Violent | F22: Nationality | G22: 1 - Not offensive | H22: 2 - Occasionally used
A23: Ghana | B23: GH0040 | C23: Ewes like Black Magic | D23: Ewes | E23: Black Magic | F23: Ethnicity | G23: 1 - Not offensive | H23: 3 - Commonly used | J23: Juju | K23: Black Magic
A24: Ghana | B24: GH0040 | C24: Ashantis are materialistic | D24: Ashanti | E24: Materialistic | F24: Ethnicity | G24: 1 - Not offensive | H24: 3 - Commonly used
A25: Ghana | B25: GH0040 | C25: Muslims are viewed as aggressive people | D25: Muslims | E25: Aggressive | F25: Religion | G25: 3 - Slightly offensive | H25: 3 - Commonly used
A26: Ghana | B26: GH0040 | C26: Ga people are aggressive | D26: Gas | E26: Aggressive | F26: Ethnicity | G26: 3 - Slightly offensive | H26: 3 - Commonly used
A27: Ghana | B27: GH0040 | C27: Northerners are viewed as uneducated | D27: Northerners | E27: Uneducated | F27: Region | G27: 3 - Slightly offensive | H27: 4 - Extremely prevalent/popular
A28: Ghana | B28: GH0040 | C28: People view southerners as well-educated | D28: Southerners | E28: Well-educated | F28: Region | G28: 1 - Not offensive | H28: 3 - Commonly used
A29: Ghana | B29: GH0040 | C29: Women are expected to be submissive | D29: Women | E29: Submissive | F29: Gender | G29: 5 - Extremely offensive | H29: 4 - Extremely prevalent/popular
A30: Ghana | B30: GH0040 | C30: Men are expected to be authoritative | D30: Men | E30: Authoritative | F30: Gender | G30: 5 - Extremely offensive | H30: 4 - Extremely prevalent/popular
A31: Ghana | B31: GH0040 | C31: Politicians are corrupt | D31: Politicians | E31: Corrupt | F31: Profession | G31: 1 - Not offensive | H31: 4 - Extremely prevalent/popular
A32: Ghana | B32: GH0040 | C32: Police are corrupt | D32: Police | E32: Corrupt | F32: Profession | G32: 1 - Not offensive | H32: 4 - Extremely prevalent/popular
A33: Ghana | B33: GH0065 | C33: Nurses don't respect their patients | D33: Nurses | E33: Don't respect patients | F33: Profession | G33: 3 - Slightly offensive | H33: 3 - Commonly used
A34: Ghana | B34: GH0065 | C34: Teachers are well-informed because they are always in class | D34: Teachers | E34: Well-informed | F34: Profession | G34: 1 - Not offensive | H34: 4 - Extremely prevalent/popular
A35: Ghana | B35: GH0065 | C35: Teachers are stingy | D35: Teachers | E35: Stingy | F35: Profession | G35: 1 - Not offensive | H35: 3 - Commonly used
... A56: Ghana | B56: GH0056 | C56: Muslims are wicked and their religion is spread by the sword | D56: Islam | E56: Spread by the sword | F56: Religion | G56: 5 - Extremely offensive | H56: 4 - Extremely prevalent/popular
A57: Ghana | B57: GH0056 | C57: All Akans love foods that have a strong smell | D57: Akans | E57: Love strong-smelling foods | F57: Ethnicity | G57: 1 - Not offensive | H57: 3 - Commonly used | I57: An example given was grasscutter faeces that are also thought to be medicinal
A58: Ghana | B58: GH0056 | C58: It is considered that Ashantis are arrogant and love to show off their wealth | D58: Ashantis | E58: Arrogant, show off wealth | F58: Ethnicity | G58: 4 - Somewhat offensive | H58: 2 - Occasionally used
A59: Ghana | B59: GH0056 | C59: Ashantis have a problem with their 'R' being interchanged with their 'L' | D59: Ashantis | E59: Interchange 'R' and 'L' when they speak | F59: Ethnicity | G59: 5 - Extremely offensive | H59: 4 - Extremely prevalent/popular
A60: Ghana | B60: GH0056 | C60: It is considered that the female's office is the kitchen | D60: Women | E60: Kitchen | F60: Gender | G60: 3 - Slightly offensive | H60: 2 - Occasionally used
A61: Ghana | B61: GH0056 | C61: Women are considered to be the ones to nurture and train the kids | D61: Women | E61: Nurture and train kids | F61: Gender | G61: 3 - Slightly offensive | H61: 1 - Rarely used
A62: Ghana | B62: GH0056 | C62: Men are considered to be the ones to provide financial support | D62: Men | E62: Provide financially | F62: Gender | G62: 3 - Slightly offensive | H62: 1 - Rarely used
A63: Ghana | B63: GH0056 | C63: Anyone who dresses in long kaftans and smocks are seen as muslims or from the North | D63: People Who Wear Smocks and long Kaftans | E63: Northerners or Muslim | F63: Dressing | G63: 5 - Extremely offensive | H63: 3 - Commonly used | J63: Jalabia | K63: Long Kaftan
A64: Ghana | B64: GH0027 | C64: All police personnel are corrupt | D64: Police | E64: Corrupt | F64: Profession | G64: 1 - Not offensive | H64: 4 - Extremely prevalent/popular
A65: Ghana | B65: GH0027 | C65: Women are believed to be sleeping around when they own property at a younger age | D65: Young women who own property | E65: Sleep around | F65: Economic Status, Age, Gender | G65: 4 - Somewhat offensive | H65: 2 - Occasionally used
A66: Ghana | B66: GH0027 | C66: Northerners are the ones who work in the mortuary | D66: Northerners | E66: Mortuary workers | F66: Region | G66: 3 - Slightly offensive | H66: 2 - Occasionally used
A67: Ghana | B67: GH0027 | C67: Northern women are known for carrying loads on their heads for money | D67: Northern women | E67: Carry loads on their heads for money | F67: Region, Gender | G67: 2 - Unsure | H67: 4 - Extremely prevalent/popular | J67: Kayayei | K67: Female head porters
A68: Ghana | B68: GH0027 | C68: All Gas care about is their meal for the day | D68: Gas | E68: Only care about daily meal | F68: Ethnicity | G68: 4 - Somewhat offensive | H68: 2 - Occasionally used
A69: Ghana | B69: GH0027 | C69: Ga women are loudly quarrelsome | D69: Ga women | E69: Loud | F69: Ethnicity, Gender | G69: 5 - Extremely offensive | H69: 3 - Commonly used
A70: Ghana | B70: GH0027 | C70: Ga women are loudly quarrelsome | D70: Ga women | E70: Quarrelsome | F70: Ethnicity, Gender | G70: 5 - Extremely offensive | H70: 3 - Commonly used
A71: Ghana | B71: GH0027 | C71: Ewes like Black magic | D71: Ewes | E71: Like black magic | F71: Ethnicity | G71: 5 - Extremely offensive | H71: 2 - Occasionally used | J71: Juju | K71: Black Magic
A72: Ghana | B72: GH0027 | C72: Muslims get angry quickly | D72: Muslims | E72: Quickly Angered | F72: Religion | G72: 2 - Unsure | H72: 3 - Commonly used
A73: Ghana | B73: GH0027 | C73: Muslims fight you when you don't see eye-to-eye with them | D73: Muslims | E73: Fight when disagreed with | F73: Religion | G73: 2 - Unsure | H73: 3 - Commonly used
A74: Ghana | B74: GH0027 | C74: Ghanaian politicians are so corrupt | D74: Ghanaian politicians | E74: Corrupt | F74: Nationality, Profession | G74: 1 - Not offensive | H74: 3 - Commonly used
A75: Ghana | B75: GH0002 | C75: Lawyers are liars | D75: Lawyers | E75: Liars | F75: Profession | G75: 5 - Extremely offensive | H75: 2 - Occasionally used
A76: Ghana | B76: GH0002 | C76: Northerners are hardworking | D76: Northerners | E76: Hardworking | F76: Region | G76: 1 - Not offensive | H76: 4 - Extremely prevalent/popular
A77: Ghana | B77: GH0002 | C77: Chinese like cheap labour | D77: Chinese | E77: Like Cheap Labour | F77: Nationality | G77: 4 - Somewhat offensive | H77: 3 - Commonly used
A78: Ghana | B78: GH0002 | C78: Nigerians are criminals | D78: Nigerians | E78: Criminals | F78: Nationality | G78: 5 - Extremely offensive | H78: 4 - Extremely prevalent/popular
A79: Ghana | B79: GH0002 | C79: Akyems prefer business to education | D79: Akyems | E79: Prefer business to education | F79: Ethnicity | G79: 5 - Extremely offensive | H79: 4 - Extremely prevalent/popular
A80: Ghana | B80: GH0002 | C80: Ghanains think the Togolese are best in construction | D80: Togolese | E80: Best in construction | F80: Nationality, Profession | G80: 1 - Not offensive | H80: 3 - Commonly used
A81: Ghana | B81: GH0002 | C81: Women don't belong in the engineering field | D81: Women | E81: Don't belong to engineering field | F81: Gender | G81: 5 - Extremely offensive | H81: 4 - Extremely prevalent/popular
A82: Ghana | B82: GH0002 | C82: Women should not be part of decision-making | D82: Women | E82: Not to be part of decision-making | F82: Gender | G82: 5 - Extremely offensive | H82: 2 - Occasionally used
A83: Ghana | B83: GH0002 | C83: Women cannot be leaders | D83: Women | E83: Cannot be leaders | F83: Gender | G83: 5 - Extremely offensive | H83: 3 - Commonly used
A84: Ghana | B84: GH0002 | C84: Farmers are poor people | D84: Farmers | E84: Poor | F84: Profession | G84: 5 - Extremely offensive | H84: 2 - Occasionally used
A85: Ghana | B85: GH0002 | C85: Those that fail in B.E.C.E. always end up in Technical schools | D85: Junior High School Failures | E85: Attend Technical Schools | F85: Education | G85: 5 - Extremely offensive | H85: 4 - Extremely prevalent/popular | J85: B.E.C.E | K85: Junior High School Exams (Basic Education Certificate Examinations)
A86: Ghana | B86: GH0015 | C86: People from the North are not ambitious | D86: Northerners | E86: Not ambitious | F86: Region | G86: 4 - Somewhat offensive | H86: 3 - Commonly used
A87: Ghana | B87: GH0015 | C87: Ashanti women are hardworking | D87: Ashanti Women | E87: Hardworking | F87: Ethnicity, Gender | G87: 1 - Not offensive | H87: 3 - Commonly used
A88: Ghana | B88: GH0015 | C88: Northern men are not caring | D88: Northern Men | E88: Not caring | F88: Region, gender | G88: 5 - Extremely offensive | H88: 4 - Extremely prevalent/popular
A89: Ghana | B89: GH0015 | C89: Women are ambitious | D89: Women | E89: Ambitious | F89: Gender | G89: 5 - Extremely offensive | H89: 4 - Extremely prevalent/popular
A90: Ghana | B90: GH0015 | C90: Muslims are seen to be aggressive | D90: Muslims | E90: Aggressive | F90: Religion | G90: 5 - Extremely offensive | H90: 4 - Extremely prevalent/popular
A91: Ghana | B91: GH0015 | C91: Female lawyers are difficult to deal with | D91: Female Lawyers | E91: Difficult | F91: Gender, Profession | G91: 5 - Extremely offensive | H91: 4 - Extremely prevalent/popular
A92: Ghana | B92: GH0015 | C92: Northern women are submissive | D92: Northern Women | E92: Submissive | F92: Ethnicity, Gender | G92: 1 - Not offensive | H92: 4 - Extremely prevalent/popular
A93: Ghana | B93: GH0015 | C93: Policewomen are difficult to deal with | D93: Policewomen | E93: Difficult | F93: Profession ,Gender | G93: 5 - Extremely offensive | H93: 4 - Extremely prevalent/popular
A94: Ghana | B94: GH0015 | C94: Doctors are unfaithful in relationships | D94: Doctors | E94: Unfaithful (in relationships) | F94: Profession | G94: 5 - Extremely offensive | H94: 4 - Extremely prevalent/popular
A95: Ghana | B95: GH0015 | C95: Gas are very aggressive | D95: Gas | E95: Aggressive | F95: Ethnicity | G95: 5 - Extremely offensive | H95: 4 - Extremely prevalent/popular
A96: Ghana | B96: GH0022 | C96: Men claim to be superior | D96: Men | E96: Superior | F96: Gender | G96: 3 - Slightly offensive | H96: 3 - Commonly used
A97: Ghana | B97: GH0022 | C97: Southerners have a cunning way of luring you into buying their items or goods | D97: Southerners | E97: Cunning salesmen | F97: Region | G97: 1 - Not offensive | H97: 3 - Commonly used
... A103: Ghana | B103: GH0022 | C103: Muslims don't allow their wards to marry from Christian families unless they convert | D103: Muslims | E103: Do not allow marriages to Christians unless they convert | F103: Religion | G103: 5 - Extremely offensive | H103: 4 - Extremely prevalent/popular
A104: Ghana | B104: GH0051 | C104: People think it's only Northerners that live in the Zongo community | D104: Northerners | E104: Live in the Zongo community | F104: Region | G104: 3 - Slightly offensive | H104: 3 - Commonly used | J104: Zongo | K104: Muslim/ Northern township/ community
A105: Ghana | B105: GH0051 | C105: Anglican church members like alcohol | D105: Anglicans | E105: Like alcohol | F105: Religion | G105: 4 - Somewhat offensive | H105: 2 - Occasionally used
A106: Ghana | B106: GH0051 | C106: Ewes are wicked | D106: Ewes | E106: Wicked | F106: Ethnicity | G106: 3 - Slightly offensive | H106: 4 - Extremely prevalent/popular
A107: Ghana | B107: GH0051 | C107: Ewes like traditional medicine | D107: Ewes | E107: Like traditional Medicine | F107: Ethnicity | G107: 3 - Slightly offensive | H107: 4 - Extremely prevalent/popular | J107: Juju | K107: traditional medicine
A108: Ghana | B108: GH0051 | C108: Police officers in Ghana like bribes too much | D108: Ghanaian Police officers | E108: Like bribes | F108: Nationality, profession | G108: 1 - Not offensive | H108: 4 - Extremely prevalent/popular
A109: Ghana | B109: GH0051 | C109: Police officers are alcoholic | D109: Police officers | E109: Alcoholic | F109: Profession | G109: 1 - Not offensive | H109: 4 - Extremely prevalent/popular
A110: Ghana | B110: GH0051 | C110: Ewe men are caring | D110: Ewe men | E110: Caring | F110: Ethnicity, gender | G110: 1 - Not offensive | H110: 2 - Occasionally used
A111: Ghana | B111: GH0051 | C111: Gas don't like work | D111: Gas | E111: Dislike work | F111: Ethnicity | G111: 3 - Slightly offensive | H111: 3 - Commonly used
A112: Ghana | B112: GH0051 | C112: Northerners don't accept marriage with other tribes in Ghana | D112: Northerners | E112: Don't allow marriages outside their tribes | F112: Region | G112: 4 - Somewhat offensive | H112: 3 - Commonly used
A113: Ghana | B113: GH0051 | C113: Gas usually pick trading over schooling | D113: Gas | E113: Prefer trading to schooling | F113: Ethnicity | G113: 3 - Slightly offensive | H113: 3 - Commonly used
A114: Ghana | B114: GH0082 | C114: NPP belongs to the Ashantis | D114: Ashantis | E114: New Patriotic Party | F114: Ethnicity | G114: 1 - Not offensive | H114: 4 - Extremely prevalent/popular | J114: NPP | K114: New Patriotic Party
A115: Ghana | B115: GH0082 | C115: Ewes are affiliated to the NDC | D115: Ewes | E115: National Democratic Congress | F115: Ethnicity | G115: 1 - Not offensive | H115: 4 - Extremely prevalent/popular | J115: NDC | K115: National Democratic Congress
A116: Ghana | B116: GH0082 | C116: Tribes in the Northern Region don't school | D116: Northerners | E116: No schooling | F116: Region | G116: 3 - Slightly offensive | H116: 2 - Occasionally used
A117: Ghana | B117: GH0082 | C117: Northern Women don't do anything apart from being in the kitchen | D117: Northern Women | E117: Always in kitchen | F117: Region, Gender | G117: 5 - Extremely offensive | H117: 3 - Commonly used
A118: Ghana | B118: GH0082 | C118: Various groups of people from the southern parts are known for fishing | D118: Southerners | E118: Always Fishing | F118: Region | G118: 1 - Not offensive | H118: 2 - Occasionally used
A119: Ghana | B119: GH0082 | C119: Highlife musicians are profane | D119: Musicians | E119: Profane | F119: Profession | G119: 3 - Slightly offensive | H119: 3 - Commonly used
A120: Ghana | B120: GH0082 | C120: Fantis are more or less very fluent in English | D120: Fantes | E120: Very fluent | F120: Ethnicity | G120: 4 - Somewhat offensive | H120: 2 - Occasionally used
A121: Ghana | B121: GH0082 | C121: No matter how a woman is educated in some Ga communities, she has to get approval from a man for certain things like buying land | D121: Ga Women | E121: Must seek male approval | F121: Ethnicity, Gender | G121: 4 - Somewhat offensive | H121: 4 - Extremely prevalent/popular
A122: Ghana | B122: GH0082 | C122: The Ewe land is full of dark medicine | D122: Ewe Land | E122: Dark Medicine | F122: Ethnicity, Region | G122: 4 - Somewhat offensive | H122: 3 - Commonly used | J122: Juju | K122: Dark medicine/ Black magic
A123: Ghana | B123: GH0082 | C123: Remote villages are deprived of education | D123: Remote Villages | E123: Education Deprived | F123: Location, Region | G123: 4 - Somewhat offensive | H123: 3 - Commonly used
A124: Ghana | B124: GH0094 | C124: African traditionalists kill for instant justice | D124: African Traditionalists | E124: Kill for justice | F124: Continent, Profession | G124: 5 - Extremely offensive | H124: 4 - Extremely prevalent/popular
A125: Ghana | B125: GH0094 | C125: Ewes like Juju | D125: Ewes | E125: Like Juju-fetish | F125: Ethnicity | G125: 4 - Somewhat offensive | H125: 2 - Occasionally used | J125: Juju | K125: Fetish/ Black magic
...

Sheet safari_multilingual
A1: Participant Information | C1: Multilingual – Stereotype Breakdown | F1: English - Captured Stereotypes | G1: English - Stereotype Breakdown | J1: Q2. Offensiveness | K1: Q3. Prevalence | L1: Additional Comments and Context
A2: Country Name | B2: Unique Identifier | C2: Target Language | D2: Stereotype Identity Term | E2: Stereotype Attribute | F2: Complete Stereotype sentence in English mentioned by the participant | G2: Stereotype Identity Term | H2: Stereotype Attribute | I2: Stereotype Identity Axis | J2: How offensive is this stereotype? (1-5) | K2: How widely used/common/popular is this stereotype? (1-4) | L2: Any additional context or background that could help understand the stereotype
A3: Ghana | B3: GH0019 | C3: Dagbani | D3: wulinluhulipolo nima | E3: Bɛ jɛ shikuru / bɛ baŋsim bɔbu | F3: People from the Upper West Region don't like schooling | G3: People From Upper West | H3: Dislike schooling | I3: Region | J3: 5 - Extremely offensive | K3: 1 - Rarely used
A4: Ghana | B4: GH0019 | C4: Dagbani | D4: Tuduŋɔnanima | E4: nyɛla musulminima | F4: People from the North are perceived to be Muslims | G4: Northeners | H4: Muslim | I4: Region | J4: 4 - Somewhat offensive | K4: 3 - Commonly used
A5: Ghana | B5: GH0019 | C5: Dagbani | D5: tuduŋɔnanima | E5: Biɛ | F5: Northerners are ugly | G5: Northeners | H5: Ugly | I5: Region | J5: 5 - Extremely offensive | K5: 1 - Rarely used
A6: Ghana | B6: GH0019 | C6: Dagbani | D6: Ankanchinima | E6: ŋuhibu | F6: Gas are loud | G6: Gas | H6: Loud | I6: Ethnicity | J6: 5 - Extremely offensive | K6: 4 - Extremely prevalent/popular
A7: Ghana | B7: GH0019 | C7: Dagbani | D7: Ankaranchi nima | E7: Vinyaɣinima | F7: Gas are lazy | G7: Gas | H7: Lazy | I7: Ethnicity | J7: 3 - Slightly offensive | K7: 3 - Commonly used
A8: Ghana | B8: GH0019 | C8: Dagbani | D8: Doo | E8: politisanima | F8: Politics is meant for men | G8: Men | H8: Politicians | I8: Gender | J8: 4 - Somewhat offensive | K8: 3 - Commonly used
A9: Ghana | B9: GH0019 | C9: Dagbani | D9: Dab'ba, biɛ Doo | E9: Tuuŋ'banda | F9: All Engineering work is meant for men | G9: Men | H9: Engineers | I9: Gender | J9: 4 - Somewhat offensive | K9: 3 - Commonly used
A10: Ghana | B10: GH0019 | C10: Dagbani | D10: Paɣ'ba / biɛ paɣa | E10: Daaŋa | F10: Women are meant to be in the kitchen | G10: Women | H10: Kitchen work | I10: Gender | J10: 5 - Extremely offensive | K10: 4 - Extremely prevalent/popular
A11: Ghana | B11: GH0019 | C11: Dagbani | D11: paɣa / biɛ paɣ'ba | E11: Doɣ'tɛ | F11: Nursing is meant for women | G11: Women | H11: Nursing | I11: Gender | J11: 4 - Somewhat offensive | K11: 3 - Commonly used
A12: Ghana | B12: GH0019 | C12: Dagbani | D12: Ghananima | E12: Suhudoo | F12: Ghanaians are peaceful people | G12: Ghanaians | H12: Peaceful | I12: Nationality | J12: 1 - Not offensive | K12: 3 - Commonly used
A13: Ghana | B13: GH0099 | C13: Dagbani | D13: Tuduŋɔna nima | E13: gbinyaɣinima | F13: All Northerners are lazy | G13: Northeners | H13: Lazy | I13: Region | J13: 5 - Extremely offensive | K13: 3 - Commonly used
A14: Ghana | B14: GH0099 | C14: Dagbani | D14: Tuduŋɔna nima | E14: Mali niŋkuusinima | F14: All Northerners are violent | G14: Northeners | H14: Violent | I14: Region | J14: 3 - Slightly offensive | K14: 3 - Commonly used
A15: Ghana | B15: GH0099 | C15: Dagbani | D15: kambɔnsi | E15: narimba zaŋ'chaŋ yaltɔga polo | F15: Ashanti people like cursing people | G15: Ashantis | H15: Like cursing people | I15: Ethnicity | J15: 1 - Not offensive | K15: 4 - Extremely prevalent/popular | L15: This refers to curses wishing harm or bad consequences on people
A16: Ghana | B16: GH0099 | C16: Dagbani | D16: Nanjɛriyanima | E16: mali Kɔriŋfahili, biɛ ninvuɣ'nyoya | F16: Nigerians are fraudsters | G16: Nigerians | H16: Fraudsters | I16: Nationality | J16: 3 - Slightly offensive | K16: 4 - Extremely prevalent/popular
A17: Ghana | B17: GH0099 | C17: Dagbani | D17: Ibonima ban yi nanjeriya bɔbili | E17: Mali nimohipam nituma tumbu | F17: Igbos from Nigeria are hardworking | G17: Igbos | H17: Hardworking | I17: Ethnicity | J17: 1 - Not offensive | K17: 3 - Commonly used
A18: Ghana | B18: GH0099 | C18: Dagbani | D18: musulminima | E18: Bɛ jɛ shikuru / biɛ bansim bɔbu | F18: Mulims don't like education | G18: Muslims | H18: Dislike Education | I18: Religion | J18: 5 - Extremely offensive | K18: 4 - Extremely prevalent/popular
A19: Ghana | B19: GH0099 | C19: Dagbani | D19: musulminima | E19: Bɛ jɛ ni bibihi ban nya bipɔɣ'si kuli ban ka bɛ dadiini puuni | F19: Muslims don't like their daughters to marry from other religions | G19: Muslims | H19: Dislike daughters marrying from other religions | I19: Religion | J19: 1 - Not offensive | K19: 4 - Extremely prevalent/popular
A20: Ghana | B20: GH0099 | C20: Dagbani | D20: paɣ'ba ban nya kpamba | E20: Borila dɛde | F20: Female bosses are strict | G20: Female Bosses | H20: Strict | I20: Gender, Profession | J20: 3 - Slightly offensive | K20: 3 - Commonly used
A21: Ghana | B21: GH0099 | C21: Dagbani | D21: politisanima | E21: nyɛla ʒirinima | F21: Policticians are liars | G21: Politicians | H21: Liars | I21: Profession | J21: 5 - Extremely offensive | K21: 4 - Extremely prevalent/popular
A22: Ghana | B22: GH0099 | C22: Dagbani | D22: Nanjariyanima | E22: ninkuunsinima | F22: Nigerians are violent | G22: Nigerians | H22: Violent | I22: Nationality | J22: 1 - Not offensive | K22: 2 - Occasionally used
A23: Ghana | B23: GH0040 | C23: Twi | D23: Ayigbefoɔ | E23: nnurosɛm | F23: Ewes like Black Magic | G23: Ewes | H23: Black Magic | I23: Ethnicity | J23: 1 - Not offensive | K23: 3 - Commonly used
A24: Ghana | B24: GH0040 | C24: Twi | D24: Asantefoɔ | E24: ahuhudeyɛ | F24: Ashantis are materialistic | G24: Ashanti | H24: Materialistic | I24: Ethnicity | J24: 1 - Not offensive | K24: 3 - Commonly used
A25: Ghana | B25: GH0040 | C25: Twi | D25: Nkramofoɔ | E25: Wɔyɛ anioden ne patapaa | F25: Muslims are viewed as aggressive people | G25: Muslims | H25: Aggressive | I25: Religion | J25: 3 - Slightly offensive | K25: 3 - Commonly used
A26: Ghana | B26: GH0040 | C26: Twi | D26: Nkranfoɔ | E26: Wɔyɛ anioden ne patapaa | F26: Ga people are aggressive | G26: Gas | H26: Aggressive | I26: Ethnicity | J26: 3 - Slightly offensive | K26: 3 - Commonly used
A27: Ghana | B27: GH0040 | C27: Twi | D27: ɛsrɛmfoɔ | E27: Wonnim nhoma | F27: Northerners are viewed as uneducated | G27: Northerners | H27: Uneducated | I27: Region | J27: 3 - Slightly offensive | K27: 4 - Extremely prevalent/popular
... A56: Ghana | B56: GH0056 | C56: Twi | D56: Nkramofoɔ | E56: Atirimuɔden | F56: Muslims are wicked and their religion is spread by the sword | G56: Muslims | H56: Wicked | I56: Religion | J56: 5 - Extremely offensive | K56: 4 - Extremely prevalent/popular
A57: Ghana | B57: GH0056 | C57: Twi | D57: Asantefoɔ | E57: Dɔ nnuan a ne ehwa ano yɛ den | F57: All Akans love foods that have a strong smell | G57: Akans | H57: Love strong-smelling foods | I57: Ethnicity | J57: 1 - Not offensive | K57: 3 - Commonly used | L57: An example given was grasscutter faeces that are also thought to be medicinal
A58: Ghana | B58: GH0056 | C58: Twi | D58: Asantefoɔ | E58: ahantan, akɛsesɛm | F58: It is considered that Ashantis are arrogant and love to show off their wealth | G58: Ashantis | H58: Arrogant, show off wealth | I58: Ethnicity | J58: 4 - Somewhat offensive | K58: 2 - Occasionally used
A59: Ghana | B59: GH0056 | C59: Twi | D59: Asantefoɔ | E59: Sesa ‘R’ ne ‘L’ sɛ wɔrekasa | F59: Ashantis have a problem with their 'R' being interchanged with their 'L' | G59: Ashantis | H59: Interchange 'R' and 'L' when they speak | I59: Ethnicity | J59: 5 - Extremely offensive | K59: 4 - Extremely prevalent/popular
A60: Ghana | B60: GH0056 | C60: Twi | D60: Mmea | E60: Mukaase | F60: It is considered that the female's office is the kitchen | G60: Women | H60: Kitchen | I60: Gender | J60: 3 - Slightly offensive | K60: 2 - Occasionally used
A61: Ghana | B61: GH0056 | C61: Twi | D61: Mmea | E61: tete mmofra | F61: Women are considered to be the ones to nurture and train the kids | G61: Women | H61: Nurture and train kids | I61: Gender | J61: 3 - Slightly offensive | K61: 1 - Rarely used
A62: Ghana | B62: GH0056 | C62: Twi | D62: Mmarima | E62: yi sika de hwɛ fie | F62: Men are considered to be the ones to provide financial support | G62: Men | H62: Provide financially | I62: Gender | J62: 3 - Slightly offensive | K62: 1 - Rarely used
A63: Ghana | B63: GH0056 | C63: Twi | D63: Wɔn a wɔhyɛ batakari ne Kaftan atenten | E63: Muslimfoɔ, ɛsrɛmfoɔ | F63: Anyone who dresses in long kaftans and smocks are seen as muslims or from the North | G63: People Who Wear Smocks and long Kaftans | H63: Northerners or Muslim | I63: Clothing Choice | J63: 5 - Extremely offensive | K63: 3 - Commonly used
A64: Ghana | B64: GH0027 | C64: Ga | D64: Polisifonyo (Amralo) | E64: Ju kɛ fɔ̃ | F64: All police personnel are corrupt | G64: Police | H64: Corrupt | I64: Profession | J64: 1 - Not offensive | K64: 4 - Extremely prevalent/popular
A65: Ghana | B65: GH0027 | C65: Ga | D65: Oblayei nii yɔɔ nibii | E65: Wɔɔ he he fɛɛ he | F65: Women are believed to be sleeping around when they own property at a younger age | G65: Young women who own property | H65: Sleep around | I65: Economic Status, Age, Gender | J65: 4 - Somewhat offensive | K65: 2 - Occasionally used
A66: Ghana | B66: GH0027 | C66: Ga | D66: Kooyigbɛ bii | E66: Gbohiiashitee nitsulɔi | F66: Northerners are the ones who work in the mortuary | G66: Northerners | H66: Mortuary workers | I66: Region | J66: 3 - Slightly offensive | K66: 2 - Occasionally used
A67: Ghana | B67: GH0027 | C67: Ga | D67: Kooyigbɛ bii yei | E67: kaya yei | F67: Northern women are known for carrying loads on their heads for money | G67: Northern women | H67: Carry loads on their heads for money | I67: Region, Gender | J67: 2 - Unsure | K67: 4 - Extremely prevalent/popular
A68: Ghana | B68: GH0027 | C68: Ga | D68: Gamɛi | E68: Daa gbi niyenii pɛ he susumɔ | F68: All Gas care about is their meal for the day | G68: Gas | H68: Only care about daily meal | I68: Ethnicity | J68: 4 - Somewhat offensive | K68: 2 - Occasionally used
A69: Ghana | B69: GH0027 | C69: Ga | D69: Gayei | E69: Belɛ béi | F69: Ga women are loudly quarrelsome | G69: Ga women | H69: Loud | I69: Ethnicity, Gender | J69: 5 - Extremely offensive | K69: 3 - Commonly used
... A208: Ghana | B208: GH0211 | C208: Ga | D208: ayigbemɛi | E208: amɛ waa mɛi ni jeee ayigbe wielɔi lɛ | F208: Ewes are unaccomodating when you can't speak their language | G208: Ewes | H208: Unaccomodating of non-Ewe speakers | I208: Ethnicity | J208: 5 - Extremely offensive | K208: 2 - Occasionally used
A209: Ghana | B209: GH0211 | C209: Ga | D209: Jarayelilɔi | E209: amɛhɔ̃ɔ nibii yɛ jara fɛɛ jara ni amɛnuɔ he akɛ amɛsumɔɔ nɔ | F209: Traders sell their products at whatever price they feel like | G209: Traders | H209: Sell products at whatever price they feel like | I209: Profession | J209: 5 - Extremely offensive | K209: 4 - Extremely prevalent/popular | L209: In other words, traders are believed to price products without any kind of control, regard for anyone or any particular logic
A210: Ghana | B210: GH0211 | C210: Ga | D210: yei | E210: shiakwɛlɔi | F210: Women are housekeepers | G210: Women | H210: Housekeepers | I210: Gender | J210: 1 - Not offensive | K210: 4 - Extremely prevalent/popular
A211: Ghana | B211: GH0211 | C211: Ga | D211: ashantemɛi | E211: NPP bii | F211: The Akans own NPP | G211: Akans | H211: NPP | I211: Ethnicity | J211: 1 - Not offensive | K211: 4 - Extremely prevalent/popular
A212: Ghana | B212: GH0211 | C212: Ga | D212: Hii | E212: nibii ni he hiaa yɛ wekulɛ mli | F212: Men do the important things in the family | G212: Men | H212: Do the important things in the family | I212: Gender | J212: 1 - Not offensive | K212: 2 - Occasionally used
A213: Ghana | B213: GH0209 | C213: Twi | D213: Asɔfoɔ | E213: atorofoɔ | F213: Many pastors today are liars | G213: Pastors | H213: Liars | I213: Religion | J213: 5 - Extremely offensive | K213: 4 - Extremely prevalent/popular
A214: Ghana | B214: GH0209 | C214: Twi | D214: Nkramofoɔ | E214: biribiara mfa wɔn ho | F214: Muslims are simple | G214: Muslims | H214: Simple | I214: Religion | J214: 1 - Not offensive | K214: 4 - Extremely prevalent/popular
A215: Ghana | B215: GH0209 | C215: Twi | D215: Nkranfoɔ | E215: nhyɛsoɔ | F215: Gas are overly assertive | G215: Gas | H215: Assertive | I215: Ethnicity | J215: 4 - Somewhat offensive | K215: 4 - Extremely prevalent/popular
A216: Ghana | B216: GH0209 | C216: Twi | D216: Nkranfoɔ | E216: sɛe sika wɔ ayiyɛ ho | F216: Gas would rather spend on funerals than help the poor | G216: Gas | H216: Spend on funerals | I216: Ethnicity | J216: 1 - Not offensive | K216: 4 - Extremely prevalent/popular
A217: Ghana | B217: GH0209 | C217: Twi | D217: Ayigbefoɔ | E217: duabɔ | F217: Ewes like to pronounce curses on people | G217: Ewes | H217: Curse people | I217: Ethnicity | J217: 3 - Slightly offensive | K217: 4 - Extremely prevalent/popular
A218: Ghana | B218: GH0209 | C218: Twi | D218: Mfantifoɔ | E218: adwumaden yɛfo | F218: Fantis are hard workers | G218: Fantis | H218: Hard-workers | I218: Ethnicity | J218: 1 - Not offensive | K218: 4 - Extremely prevalent/popular
A219: Ghana | B219: GH0209 | C219: Twi | D219: Nɛɛsefoɔ | E219: pɛ sika | F219: Nurses like money more than human life | G219: Nurses | H219: Like money | I219: Profession | J219: 1 - Not offensive | K219: 4 - Extremely prevalent/popular
A220: Ghana | B220: GH0209 | C220: Twi | D220: Amanyɔfo | E220: bɛn nkurɔfo bere a wohia abatow no | F220: Politicians only go close to people when they need their votes | G220: Politicians | H220: Go close to people when they need votes | I220: Profession | J220: 1 - Not offensive | K220: 4 - Extremely prevalent/popular
A221: Ghana | B221: GH0209 | C221: Twi | D221: Chorkorfoɔ | E221: wɔn nni wɔn ho ni | F221: People from Chorkor are not neet at all | G221: People from Chorkor | H221: Not neat | I221: Region | J221: 4 - Somewhat offensive | K221: 4 - Extremely prevalent/popular
... A256: Ghana | B256: GH0249 | C256: Twi | D256: Nɛɛsefoɔ mmea | E256: nguamanfoɔ | F256: Female nurses are known to be prostitutes | G256: Female nurses | H256: Prostitutes | I256: Gender, Profession | J256: 1 - Not offensive | K256: 4 - Extremely prevalent/popular
A257: Ghana | B257: GH0249 | C257: Twi | D257: Romanfoɔ | E257: abosom somfoɔ | F257: Roman Catholics are known to be idol worshippers | G257: Roman Catholics | H257: Idol worshippers | I257: Religion | J257: 1 - Not offensive | K257: 4 - Extremely prevalent/popular | L257: This line of thinking is usually due to the many artifacts during worship and reference to Saints, Mary Mother of Jesus, etc during prayers, etc
A258: Ghana | B258: GH0249 | C258: Twi | D258: Ghana apolisifoɔ | E258: adanmude | F258: Policemen in Ghana like taking bribes | G258: Policemen in Ghana | H258: Like taking bribes | I258: Profession, Region | J258: 2 - Unsure | K258: 4 - Extremely prevalent/popular
A259: Ghana | B259: GH0249 | C259: Twi | D259: Asantefoɔ | E259: wɔn pɛ sukuu kɔ | F259: Ashantis don't like going to school | G259: Ashantis | H259: Don't like going to school | I259: Ethnicity | J259: 1 - Not offensive | K259: 4 - Extremely prevalent/popular
A260: Ghana | B260: GH0249 | C260: Twi | D260: Akan mmarima | E260: Fufu | F260: An Akan man cannot live without eating fufu | G260: Akan man | H260: Cannot live without eating fufu | I260: Ethnicity, Gender | J260: 1 - Not offensive | K260: 4 - Extremely prevalent/popular
A261: Ghana | B261: GH0249 | C261: Twi | D261: Frafrafoɔ | E261: nkoa | F261: Frafra people tend to work as servants for others | G261: Frafra people | H261: Servants | I261: Ethnicity | J261: 1 - Not offensive | K261: 4 - Extremely prevalent/popular
A262: Ghana | B262: GH0249 | C262: Twi | D262: Asantefoɔ | E262: Ahantan | F262: Ashantis are proud | G262: Ashantis | H262: Proud | I262: Ethnicity | J262: 1 - Not offensive | K262: 4 - Extremely prevalent/popular
A263: Ghana | B263: GH0249 | C263: Twi | D263: Asɔfoɔ | E263: Ndaadaafo | F263: Pastors are deceivers | G263: Pastors | H263: Deceivers | I263: Religion | J263: 1 - Not offensive | K263: 4 - Extremely prevalent/popular
A264: Ghana | B264: GH0216 | C264: Ga | D264: gamɛi | E264: amɛhaa amɛ tsuji lɛ ni amɛ wɔɔ kpo nɔ | F264: Gas rent out their rooms and sleep outside | G264: Gas | H264: Rent out their rooms and sleep outside | I264: Ethnicity | J264: 5 - Extremely offensive | K264: 3 - Commonly used
A265: Ghana | B265: GH0216 | C265: Ga | D265: gamɛi | E265: efii weku lɛ sɛɛ | F265: Gas are not supportive to family members | G265: Gas | H265: Not supportive of family | I265: Ethnicity | J265: 4 - Somewhat offensive | K265: 4 - Extremely prevalent/popular
A266: Ghana | B266: GH0216 | C266: Ga | D266: gamɛi hii | E266: sumɔɔɔ nistumɔ | F266: Ga men don't like to work | G266: Ga men | H266: Don't like to work | I266: Ethnicity, Gender | J266: 5 - Extremely offensive | K266: 4 - Extremely prevalent/popular
A267: Ghana | B267: GH0216 | C267: Ga | D267: sɔnumɛi | E267: mujiŋ | F267: Muslims are too dirty | G267: Muslims | H267: Dirty | I267: Religion | J267: 1 - Not offensive | K267: 4 - Extremely prevalent/popular
A268: Ghana | B268: GH0216 | C268: Ga | D268: anagomɛi | E268: amɛ he wuɔɔ muji | F268: Nigerians are not neat at all | G268: Nigerians | H268: Not neat | I268: Nationality | J268: 1 - Not offensive | K268: 4 - Extremely prevalent/popular
A269: Ghana | B269: GH0216 | C269: Ga | D269: ayigbemɛi | E269: sulɔi / Tsofa tsulɔi | F269: Ewes like Black magic | G269: Ewes | H269: Like black magic | I269: Ethnicity | J269: 4 - Somewhat offensive | K269: 4 - Extremely prevalent/popular
... A271: Ghana | B271: GH0220 | C271: Ewe | D271: Ɛgetɔwo | E271: ƒo ɖi | F271: Gas are dirty | G271: Gas | H271: Dirty | I271: Ethnicity | J271: 4 - Somewhat offensive | K271: 4 - Extremely prevalent/popular
A272: Ghana | B272: GH0220 | C272: Ewe | D272: Ɛgetɔwo | E272: bometsilawo | F272: Gas are foolish | G272: Gas | H272: Foolish | I272: Ethnicity | J272: 3 - Slightly offensive | K272: 3 - Commonly used | L272: Reference to the practice Gas are known to have of renting out all the rooms in their house and then sleeping on a porch or some other small space. Often done in Accra where there is high demand for rooms to rent.
A273: Ghana | B273: GH0220 | C273: Ewe | D273: Ashanti nyɔnuwo | E273: lɔ̃a ŋutsu kɔkɔwo | F273: Ashanti women like tall men | G273: Ashanti women | H273: Like tall men | I273: Ethnicity, Gender | J273: 2 - Unsure | K273: 2 - Occasionally used
A274: Ghana | B274: GH0220 | C274: Ewe | D274: Ʋegbetɔwo | E274: lɔ̃a dzosasa | F274: Ewes like black magic | G274: Ewes | H274: Like black magic | I274: Ethnicity | J274: 5 - Extremely offensive | K274: 4 - Extremely prevalent/popular
A275: Ghana | B275: GH0220 | C275: Ewe | D275: Northtɔwo | E275: ƒe tagbɔ kɔ ŋutɔ | F275: Northerners are very intelligent | G275: Northerners | H275: Intelligent | I275: Region | J275: 2 - Unsure | K275: 3 - Commonly used
A276: Ghana | B276: GH0220 | C276: Ewe | D276: Fantetɔwo | E276: nye lɔlɔ̃nyawo | F276: Fantis are romantic | G276: Fantis | H276: Romantic | I276: Ethnicity | J276: 1 - Not offensive | K276: 4 - Extremely prevalent/popular
A277: Ghana | B277: GH0220 | C277: Ewe | D277: Ame siwo tso Niger | E277: la ƒo ɖi | F277: People from Niger are dirty | G277: People from Niger | H277: Dirty | I277: Nationality | J277: 5 - Extremely offensive | K277: 4 - Extremely prevalent/popular
A278: Ghana | B278: GH0220 | C278: Ewe | D278: Katolikotɔwo | E278: subɔa legbawo | F278: Catholics worship idols | G278: Catholics | H278: Worship idols | I278: Religion | J278: 5 - Extremely offensive | K278: 4 - Extremely prevalent/popular | L278: This line of thinking is usually due to the many artifacts during worship and reference to Saints, Mary Mother of Jesus, etc during prayers, etc
A279: Ghana | B279: GH0220 | C279: Ewe | D279: Ŋutsu tsralawo | E279: lɔ̃a nyɔnuvi damiwo | F279: Slim guys like fat girls | G279: Slim guys | H279: Like fat girls | I279: Appearance, Gender | J279: 1 - Not offensive | K279: 4 - Extremely prevalent/popular
A280: Ghana | B280: GH0220 | C280: Ewe | D280: Kpovitɔwo | E280: lɔ̃a zãnunana | F280: Policemen like bribes | G280: Policemen | H280: Like Bribes | I280: Profession | J280: 5 - Extremely offensive | K280: 4 - Extremely prevalent/popular
A281: Ghana | B281: GH0220 | C281: Ewe | D281: Ʋukulawo | E281: wɔa nyɔnunya | F281: Drivers are womanizers | G281: Drivers | H281: Womanizers | I281: Profession | J281: 1 - Not offensive | K281: 4 - Extremely prevalent/popular
A282: Ghana | B282: GH0220 | C282: Ewe | D282: Pastorwo viwo | E282: gblẽ | F282: Pastor/s children are spoilt | G282: Pastor's children | H282: Spoilt | I282: Religion, Age | J282: 1 - Not offensive | K282: 4 - Extremely prevalent/popular | L282: They are believed to be of bad behaviour, involved in negative practices that don't match their Pastor parent's position. This may be with or without parent's knowledge
A283: Ghana | B283: GH0220 | C283: Ewe | D283: Dzotsilawo | E283: lɔ̃a ahanono | F283: Fire Service Personnel like drinking | G283: Fire service personnel | H283: Like drinking | I283: Profession | J283: 5 - Extremely offensive | K283: 2 - Occasionally used
A284: Ghana | B284: GH0226 | C284: Ewe | D284: Kesinɔtɔwo | E284: mekpena ɖe ame dahewo ŋu o | F284: Rich men do not help poor people | G284: Rich men | H284: Do not help poor people | I284: Socio-economic status, Gender | J284: 5 - Extremely offensive | K284: 4 - Extremely prevalent/popular
A285: Ghana | B285: GH0226 | C285: Ewe | D285: Kesinɔtɔwo | E285: ƒoa nu gbegblẽ tso ame dahewo ŋu | F285: Rich men speak badly of the poor | G285: Rich men | H285: Speak badly of the poor | I285: Socio-economic status, Gender | J285: 3 - Slightly offensive | K285: 4 - Extremely prevalent/popular
A286: Ghana | B286: GH0226 | C286: Ewe | D286: Sɔlemehakplɔla siwo medze o | E286: ƒe agbenɔnɔ to vovo na nusi woɖea gbeƒãe | F286: Unqualified pastors tend to live differently from what they preach | G286: Unqualified pastors | H286: Live differently from what they preach | I286: Religion/Profession | J286: 3 - Slightly offensive | K286: 3 - Commonly used
A287: Ghana | B287: GH0226 | C287: Ewe | D287: Kpovitɔwo | E287: nye nufitifitiwɔlawo | F287: Policemen are corrupt | G287: Policemen | H287: Corrupt | I287: Profession | J287: 5 - Extremely offensive | K287: 4 - Extremely prevalent/popular
A288: Ghana | B288: GH0226 | C288: Ewe | D288: Senyalawo | E288: nye nufitifitiwɔlawo | F288: Lawyers are corrupt | G288: Lawyers | H288: Corrupt | I288: Profession | J288: 5 - Extremely offensive | K288: 4 - Extremely prevalent/popular
A289: Ghana | B289: GH0226 | C289: Ewe | D289: Sɔhɛwo | E289: nye atikevɔ̃ɖizãlawo le ŋkeke siawo me | F289: Young people these days are drug addicts | G289: Young people | H289: Drug addicts | I289: Age | J289: 5 - Extremely offensive | K289: 4 - Extremely prevalent/popular
A290: Ghana | B290: GH0226 | C290: Ewe | D290: Egbegbe nyɔnuviwo | E290: melɔ̃a dɔwɔwɔ o | F290: Girls of today do not like to work | G290: Girls | H290: Do not like to work | I290: Gender, Age | J290: 4 - Somewhat offensive | K290: 3 - Commonly used
A291: Ghana | B291: GH0226 | C291: Ewe | D291: Egbegbe nyɔnuviwo | E291: lɔ̃a ga | F291: Girls of today love money | G291: Girls | H291: Love money | I291: Gender, Age | J291: 4 - Somewhat offensive | K291: 3 - Commonly used
A292: Ghana | B292: GH0226 | C292: Ewe | D292: Sɔhɛwo | E292: ƒoa wo ɖokui ɖe adzodada me | F292: Young people are involved in robbery | G292: Young people | H292: Robbery | I292: Age | J292: 4 - Somewhat offensive | K292: 4 - Extremely prevalent/popular
A293: Ghana | B293: GH0226 | C293: Ewe | D293: Ʋegbetɔwo | E293: de suku nyuie | F293: Ewes are well-educated | G293: Ewes | H293: Well-educated | I293: Ethnicity | J293: 1 - Not offensive | K293: 4 - Extremely prevalent/popular
A294: Ghana | B294: GH0226 | C294: Ewe | D294: Akantɔwo / Ɛblutɔwo | E294: lɔ̃a adegbeƒoƒo | F294: Akans like bragging | G294: Akans | H294: Like Bragging | I294: Ethnicity | J294: 5 - Extremely offensive | K294: 4 - Extremely prevalent/popular
... A317: Ghana | B317: GH0217 | C317: Ewe | D317: Ʋegbe nyɔnuwo | E317: dze tugbe ŋutɔ | F317: Ewe ladies are beautiful | G317: Ewe ladies | H317: Beautiful | I317: Gender, Ethnicity | J317: 1 - Not offensive | K317: 3 - Commonly used
A318: Ghana | B318: GH0217 | C318: Ewe | D318: Ɛge nyɔnuwo | E318: bi ɖe ɖorkunu wɔwɔ me | F318: Ga women are good at making kenkey | G318: Ga women | H318: Good at making kenkey | I318: Ethnicity, Gender | J318: 3 - Slightly offensive | K318: 3 - Commonly used | L318: Gas have a type of kenkey they make. Other tribes have also learnt how to make it. Many people, including Ga women actually don't know how to make it.
A319: Ghana | B319: GH0217 | C319: Ewe | D319: Ŋutsu akpa gãtɔ | E319: lɔ̃a nyɔnu titriwo | F319: Most guys like thick ladies | G319: Guys | H319: Like thick ladies | I319: Gender | J319: 4 - Somewhat offensive | K319: 4 - Extremely prevalent/popular
A320: Ghana | B320: GH0217 | C320: Ewe | D320: Nigeriatɔwo | E320: wo ba gɛ aɖu | F320: Nigerians are gold-diggers | G320: Nigerians | H320: Gold-diggers | I320: Nationality | J320: 4 - Somewhat offensive | K320: 2 - Occasionally used | L320: Used in the sense of Someone associating with another for the sake of money
A321: Ghana | B321: GH0217 | C321: Ewe | D321: Hausatɔwo | E321: bi ɖe Tuo zaafi ɖaɖa me wu gbe bubu metɔwo ɖesiaɖe | F321: Hausas are better at cooking Tuo zaafi than any other tribe | G321: Hausa | H321: Better Tuo zaafi cooks than other tribes | I321: Ethnicity | J321: 1 - Not offensive | K321: 3 - Commonly used
A322: Ghana | B322: GH0217 | C322: Ewe | D322: Accra nyɔnuwo | E322: dea bubu wo ŋu wu nyɔnu siwo tso du bubuwo me | F322: Accra ladies are more respectable than ladies from other cities | G322: Accra ladies | H322: More respectable than ladies from other cities | I322: Region, gender | J322: 5 - Extremely offensive | K322: 4 - Extremely prevalent/popular
A323: Ghana | B323: GH0217 | C323: Ewe | D323: Ɛgetɔwo | E323: ƒoa nu geɖe | F323: Gas talk a lot compared to other tribes | G323: Gas | H323: Talk a lot | I323: Ethnicity | J323: 5 - Extremely offensive | K323: 3 - Commonly used
...
